audiocomplib/__init__.py
audiocomplib/audio_compressor.py
audiocomplib/audio_dynamics.py
audiocomplib/peak_limiter.py
audiocomplib/smooth_gain_reduction.c
audiocomplib/smooth_gain_reduction.cp312-win_amd64.pyd
audiocomplib/smooth_gain_reduction.pyx
audiocomplib/smooth_gain_reduction_init.py
audiocomplib/smooth_gain_reduction_py.py
audiocomplib-0.2.0.dist-info/LICENSE
audiocomplib-0.2.0.dist-info/METADATA
audiocomplib-0.2.0.dist-info/WHEEL
audiocomplib-0.2.0.dist-info/top_level.txt
audiocomplib-0.2.0.dist-info/RECORD
