Metadata-Version: 2.2
Name: audiocomplib
Version: 0.2.0
Summary: A Python library for audio dynamic compression and limiting
Author-email: Gdaliy Garmiza <gdalik@gmail.com>
Maintainer-email: Gdaliy Garmiza <gdalik@gmail.com>
License: MIT
Classifier: Programming Language :: Python :: 3.9
Classifier: Programming Language :: Python :: 3.10
Classifier: Programming Language :: Python :: 3.11
Classifier: Programming Language :: Python :: 3.12
Classifier: Programming Language :: Python :: 3.13
Requires-Python: >=3.9
License-File: LICENSE
Requires-Dist: numpy>=2
Requires-Dist: Cython>=3.0.12
